ndshapecheck/__init__.py
ndshapecheck/has_shape.py
ndshapecheck/py.typed
ndshapecheck/shape_check.py
ndshapecheck/shape_rule.py
ndshapecheck-0.2.4.dist-info/METADATA
ndshapecheck-0.2.4.dist-info/WHEEL
ndshapecheck-0.2.4.dist-info/licenses/LICENSE
ndshapecheck-0.2.4.dist-info/RECORD
