Metadata-Version: 2.4
Name: ndshapecheck
Version: 0.2.4
Summary: A library for checking the shapes of multidimensional arrays.
Author-email: Joseph Agrane <josephagrane@gmail.com>
License: Copyright 2025 Joseph Agrane
License-File: LICENSE
Requires-Python: >=3.10
